<?xml version="1.0" encoding="UTF-8"?>
<odoo>

<!-- <br/>
                                <h4 class="text-info">Colisage</h4>
                                <field name="packaging_ids" context="{'default_product_id':id}">
                                    <tree decoration-bf="True" editable="bottom">
                                        <field name="sequence" widget="handle"/>
                                        <field name="name"/>
                                        <field name="qty"/> -->
                                        <!--<field name="weight" string="Poids(kg)"/>-->
                                        <!--<field name="volume" string="Volume(m3)"/>-->
                                    <!-- </tree>

                                </field> -->


</odoo>
